RobotTracker/Tester.py
RobotTracker/TrackerDB.py
RobotTracker/__init__.py
automation_tracker-1.0.0.4.dist-info/LICENSE
automation_tracker-1.0.0.4.dist-info/METADATA
automation_tracker-1.0.0.4.dist-info/WHEEL
automation_tracker-1.0.0.4.dist-info/top_level.txt
automation_tracker-1.0.0.4.dist-info/RECORD
