Metadata-Version: 2.1
Name: automation-tracker
Version: 1.0.0.4
Summary: Robot Framework Library for Tracking Test Cases
Author: Justus Mwangi
Author-email: <mwangijustus12@gmail.com>
Keywords: python,robotframework,robotframework-library,robotframework-library,robotframework-tracking,robotframework-tracker,robotframework-tracker,robotframework-tracker
Classifier: Development Status :: 1 - Planning
Classifier: Intended Audience :: Developers
Classifier: Programming Language :: Python :: 3
Classifier: Operating System :: OS Independent
License-File: LICENSE
Requires-Dist: robotframework
Requires-Dist: requests
Requires-Dist: robotframework-requests
Requires-Dist: robotframework-jsonlibrary
Requires-Dist: robotframework-listenerlibrary
Requires-Dist: robotframework-seleniumlibrary
Requires-Dist: urllib3
Requires-Dist: robotframework-stringformat
